{
  "ticker": "7974.T",
  "name": "Nintendo",
  "sector": "Consumer Discretionary",
  "market_cap": 13755613184000.0,
  "source_list": "Nikkei225",
  "fundamentals": {
    "PE": 49.344303,
    "PB": 5.049171,
    "EV_Revenue": 10.042,
    "ROE": 0.10463,
    "ProfitMargin": 0.23933001,
    "GrossMargin": 0.60963,
    "DividendYield": 1.02,
    "DebtEquity": null,
    "CurrentRatio": 4.605,
    "QuickRatio": 3.553,
    "FreeCashFlow": -82245746688,
    "OperatingCashFlow": 12069000192,
    "FCF_Margin": -0.07060193076910094,
    "ROA": 0.05392,
    "PEG": null,
    "EV_EBITDA": 39.268,
    "BuybackYield": null,
    "PriceToFCF": -167.25014651738826
  },
  "technical_indicators": {
    "RSI_14": 51.72365543914496,
    "Momentum_10": -0.1689902830587241,
    "MACD": 128.29345149282744,
    "BB_Percent": 0.4848855018559526,
    "SMA20_above_SMA50": 1.0
  },
  "scores": {
    "ValueScore": 0.8614405892179692,
    "QualityScore": 0.4775029958064352,
    "SignalScore": 0.5465908367717771
  },
  "volatility": 0.0283719049561862,
  "beta": 0.408,
  "return_6m": 0.3049931312517688,
  "analyst_rating": {
    "recommendation": "buy",
    "analyst_count": 25,
    "target_mean_price": 12903.799
  },
  "visual_data": {
    "sparkline": [
      {
        "date": "2024-12-13",
        "price": 9124.0
      },
      {
        "date": "2024-12-16",
        "price": 9184.0
      },
      {
        "date": "2024-12-17",
        "price": 9490.0
      },
      {
        "date": "2024-12-18",
        "price": 9265.0
      },
      {
        "date": "2024-12-19",
        "price": 9410.0
      },
      {
        "date": "2024-12-20",
        "price": 9131.0
      },
      {
        "date": "2024-12-23",
        "price": 9171.0
      },
      {
        "date": "2024-12-24",
        "price": 9228.0
      },
      {
        "date": "2024-12-25",
        "price": 9200.0
      },
      {
        "date": "2024-12-26",
        "price": 9260.0
      },
      {
        "date": "2024-12-27",
        "price": 9350.0
      },
      {
        "date": "2024-12-30",
        "price": 9264.0
      },
      {
        "date": "2025-01-06",
        "price": 9070.0
      },
      {
        "date": "2025-01-07",
        "price": 9158.0
      },
      {
        "date": "2025-01-08",
        "price": 8903.0
      },
      {
        "date": "2025-01-09",
        "price": 9119.0
      },
      {
        "date": "2025-01-10",
        "price": 9248.0
      },
      {
        "date": "2025-01-14",
        "price": 9332.0
      },
      {
        "date": "2025-01-15",
        "price": 9565.0
      },
      {
        "date": "2025-01-16",
        "price": 9590.0
      },
      {
        "date": "2025-01-17",
        "price": 9181.0
      },
      {
        "date": "2025-01-20",
        "price": 8901.0
      },
      {
        "date": "2025-01-21",
        "price": 9044.0
      },
      {
        "date": "2025-01-22",
        "price": 9404.0
      },
      {
        "date": "2025-01-23",
        "price": 9559.0
      },
      {
        "date": "2025-01-24",
        "price": 9890.0
      },
      {
        "date": "2025-01-27",
        "price": 9793.0
      },
      {
        "date": "2025-01-28",
        "price": 10250.0
      },
      {
        "date": "2025-01-29",
        "price": 10190.0
      },
      {
        "date": "2025-01-30",
        "price": 10425.0
      },
      {
        "date": "2025-01-31",
        "price": 10230.0
      },
      {
        "date": "2025-02-03",
        "price": 10175.0
      },
      {
        "date": "2025-02-04",
        "price": 10400.0
      },
      {
        "date": "2025-02-05",
        "price": 10700.0
      },
      {
        "date": "2025-02-06",
        "price": 11000.0
      },
      {
        "date": "2025-02-07",
        "price": 10805.0
      },
      {
        "date": "2025-02-10",
        "price": 10935.0
      },
      {
        "date": "2025-02-12",
        "price": 10980.0
      },
      {
        "date": "2025-02-13",
        "price": 11250.0
      },
      {
        "date": "2025-02-14",
        "price": 11245.0
      },
      {
        "date": "2025-02-17",
        "price": 11395.0
      },
      {
        "date": "2025-02-18",
        "price": 11450.0
      },
      {
        "date": "2025-02-19",
        "price": 11760.0
      },
      {
        "date": "2025-02-20",
        "price": 11490.0
      },
      {
        "date": "2025-02-21",
        "price": 11455.0
      },
      {
        "date": "2025-02-25",
        "price": 11310.0
      },
      {
        "date": "2025-02-26",
        "price": 11105.0
      },
      {
        "date": "2025-02-27",
        "price": 11400.0
      },
      {
        "date": "2025-02-28",
        "price": 11160.0
      },
      {
        "date": "2025-03-03",
        "price": 11065.0
      },
      {
        "date": "2025-03-04",
        "price": 11130.0
      },
      {
        "date": "2025-03-05",
        "price": 11175.0
      },
      {
        "date": "2025-03-06",
        "price": 11385.0
      },
      {
        "date": "2025-03-07",
        "price": 10335.0
      },
      {
        "date": "2025-03-10",
        "price": 10005.0
      },
      {
        "date": "2025-03-11",
        "price": 10055.0
      },
      {
        "date": "2025-03-12",
        "price": 10160.0
      },
      {
        "date": "2025-03-13",
        "price": 10180.0
      },
      {
        "date": "2025-03-14",
        "price": 10265.0
      },
      {
        "date": "2025-03-17",
        "price": 10285.0
      },
      {
        "date": "2025-03-18",
        "price": 10270.0
      },
      {
        "date": "2025-03-19",
        "price": 10550.0
      },
      {
        "date": "2025-03-21",
        "price": 10895.0
      },
      {
        "date": "2025-03-24",
        "price": 10690.0
      },
      {
        "date": "2025-03-25",
        "price": 10765.0
      },
      {
        "date": "2025-03-26",
        "price": 11330.0
      },
      {
        "date": "2025-03-27",
        "price": 11030.0
      },
      {
        "date": "2025-03-28",
        "price": 10835.0
      },
      {
        "date": "2025-03-31",
        "price": 10110.0
      },
      {
        "date": "2025-04-01",
        "price": 10205.0
      },
      {
        "date": "2025-04-02",
        "price": 10420.0
      },
      {
        "date": "2025-04-03",
        "price": 10080.0
      },
      {
        "date": "2025-04-04",
        "price": 9977.0
      },
      {
        "date": "2025-04-07",
        "price": 9194.0
      },
      {
        "date": "2025-04-08",
        "price": 9841.0
      },
      {
        "date": "2025-04-09",
        "price": 9405.0
      },
      {
        "date": "2025-04-10",
        "price": 10505.0
      },
      {
        "date": "2025-04-11",
        "price": 10040.0
      },
      {
        "date": "2025-04-14",
        "price": 10350.0
      },
      {
        "date": "2025-04-15",
        "price": 10305.0
      },
      {
        "date": "2025-04-16",
        "price": 10040.0
      },
      {
        "date": "2025-04-17",
        "price": 10345.0
      },
      {
        "date": "2025-04-18",
        "price": 10370.0
      },
      {
        "date": "2025-04-21",
        "price": 10245.0
      },
      {
        "date": "2025-04-22",
        "price": 10175.0
      },
      {
        "date": "2025-04-23",
        "price": 10415.0
      },
      {
        "date": "2025-04-24",
        "price": 11000.0
      },
      {
        "date": "2025-04-25",
        "price": 11400.0
      },
      {
        "date": "2025-04-28",
        "price": 11435.0
      },
      {
        "date": "2025-04-30",
        "price": 11830.0
      },
      {
        "date": "2025-05-01",
        "price": 12145.0
      },
      {
        "date": "2025-05-02",
        "price": 12360.0
      },
      {
        "date": "2025-05-07",
        "price": 12350.0
      },
      {
        "date": "2025-05-08",
        "price": 12020.0
      },
      {
        "date": "2025-05-09",
        "price": 11820.0
      },
      {
        "date": "2025-05-12",
        "price": 11580.0
      },
      {
        "date": "2025-05-13",
        "price": 12005.0
      },
      {
        "date": "2025-05-14",
        "price": 11700.0
      },
      {
        "date": "2025-05-15",
        "price": 11445.0
      },
      {
        "date": "2025-05-16",
        "price": 11640.0
      },
      {
        "date": "2025-05-19",
        "price": 11620.0
      },
      {
        "date": "2025-05-20",
        "price": 11530.0
      },
      {
        "date": "2025-05-21",
        "price": 11265.0
      },
      {
        "date": "2025-05-22",
        "price": 11200.0
      },
      {
        "date": "2025-05-23",
        "price": 11800.0
      },
      {
        "date": "2025-05-26",
        "price": 11965.0
      },
      {
        "date": "2025-05-27",
        "price": 12205.0
      },
      {
        "date": "2025-05-28",
        "price": 12150.0
      },
      {
        "date": "2025-05-29",
        "price": 12330.0
      },
      {
        "date": "2025-05-30",
        "price": 11835.0
      },
      {
        "date": "2025-06-02",
        "price": 11745.0
      },
      {
        "date": "2025-06-03",
        "price": 11695.0
      },
      {
        "date": "2025-06-04",
        "price": 12090.0
      },
      {
        "date": "2025-06-05",
        "price": 11850.0
      },
      {
        "date": "2025-06-06",
        "price": 11905.0
      },
      {
        "date": "2025-06-09",
        "price": 12080.0
      },
      {
        "date": "2025-06-10",
        "price": 12105.0
      },
      {
        "date": "2025-06-11",
        "price": 11665.0
      },
      {
        "date": "2025-06-12",
        "price": 11795.0
      },
      {
        "date": "2025-06-13",
        "price": 11815.0
      }
    ],
    "current_price_data": {
      "price": 11815.0,
      "change": 20.0,
      "percent_change": 0.17
    }
  },
  "news_sentiment": {
    "summary": "Nintendo fait face à des défis majeurs, avec des bénéfices en baisse et des prévisions de ventes réduites pour sa console Switch actuelle. Les tarifs de Trump et les retards liés au Switch 2 impactent négativement l'action. Cependant, l'annonce d'un dividende et d'un fractionnement d'actions visant à attirer de nouveaux investisseurs a stimulé brièvement les cours. Les investisseurs surveillent de près les prévisions de vente du Switch 2 et l'introduction de Mario Kart World pour évaluer l'avenir de l'entreprise.",
    "sentiment_score": -0.3,
    "label": "NEGATIVE",
    "positive_ratio": 0.15,
    "neutral_ratio": 0.4,
    "negative_ratio": 0.45,
    "bullet_positive_count": 1,
    "bullet_negative_count": 0,
    "headlines": [
      {
        "title": "Nintendo Switch 2 hype leads to shortages, special store opening hours - CNBC",
        "url": "https://news.google.com/rss/articles/CBMipgFBVV95cUxQMWROSnBtUTd3QjNQQURGaC1TSGhxN29IOEFDMDBZLUZhVXNIWFMxWmI0djNHOEFveHVXYWt4OW9aaEpqS3ZWNmlRaXpNeDFMOVZNeTN5aDVKaklrQURqcVllcWUyS3FsdGlpMjJILWVrcTZNa21rdTI1MHlBWVNqbk5hbDZEam1kbGhpd0xKRDNodFFuLTctQ1hVa0xPWjVQZFJGaU930gGrAUFVX3lxTE9UX0dMVG9ib1JGa0xnbTV1X2haYmJZZGMtYlM5Zi1ScEVwdG96dV94QXN1Q3FPN1hHSlY3MUlpSW1GUEJUQ0dVLXJKZVBydnFPNmFYWnVEUmI2TWVIYlA4b3JxVmJURzh4UmVLQkI1dW1wQUt2bHdRcEJLSTkzMkhVOFRXdHRzbFpLSzFZRGRQcDExUXdRenRaVEpYMWQzZHhfS2J4YzFsNEhYWQ?oc=5",
        "label": "NEGATIVE"
      },
      {
        "title": "Nintendo's (TSE:7974) Sluggish Earnings Might Be Just The Beginning Of Its Problems - simplywall.st",
        "url": "https://news.google.com/rss/articles/CBMixwFBVV95cUxOTTltcDJvRmI4MldwNzZZemEzUFQ0d1pjUVZOeUJJcnM5LWtjRld5NXEzUVZ5M0RZR2Zpc2Zpb0JreUtaMjRac2NKUU9kTmJCOUNGSUpfNWxuMFpnYjVWbjQ5VGRST0RjMUdUeDlXaXZpUGo4SFRaUFVudjN1aWs0R29YSUkxWnNyekc4alNfT0dvc1V5eEFHMVVmUFRzNWdKZGdYOFY2Q1pTMDF0d1RuNmNBU0JUTnNMY1p4X19sZTFIQWRTWmtn0gHMAUFVX3lxTFBQdjdQUDJVaUYtTWhUNnRWYUNTUGRPLW5uZGdKbEdNZzhhSXY5SXdBa1JObm9ySzdsS2ZOSi1NQ0ktekZzRWIwMjJ1M0dPSWRiTXVydzE4cUtvLVRwNVo0Q0FzRklWMzV2cVczT0o1MkVBS0wzYXUxQnIyYkNnR0ZOSHZnVW9BbzAyZHFna3pRS1dna1BONUpuYlU1NDZWNF9JYUlhdUFFa21CVksyaDNjZUxOdkxnWDBuQjBkNlhJQlBpRTdLZ3A3SkN2cQ?oc=5",
        "label": "NEGATIVE"
      },
      {
        "title": "Nintendo stock down as Trump's tariffs weigh on gaming consoles - Yahoo Finance",
        "url": "https://news.google.com/rss/articles/CBMiiAFBVV95cUxPWHVhdVVra1dyMzg1ZXFMOUdoZU5xQ01ubG5HUWhsMnNnM0FydE92MzFaXzJOYUx1MW5obTNfemljdmNnYmFQWXNiNmNuUXpfdmVMWEh4LTNLNkxGeVlXcTFBOGtuRWpPUUpiZ3lNV1NSbGwyQThPa0NjZkxUQjJoeENUZDVENGNP?oc=5",
        "label": "NEGATIVE"
      },
      {
        "title": "Nintendo sees Switch 2 sales of 15 million units, profit rising 13% this year - Reuters",
        "url": "https://news.google.com/rss/articles/CBMilAFBVV95cUxNOHdxNDA5bUg0bDRUYU9DWHdNSkxpWkV2WmhRSkRqbGhnQzFPT2JDVnlaQVh3bHZGdXJnMWJTMnNsbkJ1aHV1M2ZWV2FWS3VoTmRxNWp5OTBrQ1FOSWlQNjg1MWQ3emZVbHdibGIwOHZKbTgxZTdSVlNyd0NHcjdaTWpVbENqQ2I1czBCWG12ZlR4SmNV?oc=5",
        "label": "POSITIVE"
      },
      {
        "title": "Microsoft enters portable gaming with new ROG Xbox Ally devices - CNBC",
        "url": "https://news.google.com/rss/articles/CBMiogFBVV95cUxNWlcyS2tFQzJjY012V19KcVpwODFNbU82ZXpKai1nV3ljT042SWlhNHA4bUJyM3VWdW1hSERZaTZtODNFSE1JZHFhYl93UjFxSndneVE5SEQ4Z0pSczN6ZFJaVkU5YXZnWjNWOVZaeFFlcG1tTW42RjNYR0d6Vk9GaXZsemNNT2J1RTBZSG9PM1JwNGJkbUhCSEZWT18yZVZxY0HSAacBQVVfeXFMTXZ1Tk9RQ3FVTmlMbE5LSUZ4TnUtRXdqU0x0VHAwZFlVTTlkR3d4SmZWdmxoZUZrd0dqd2FncUJrSTdkMm5rUGVzSXY5LXlnemxNRzhtaHY1bjRlWl93Y3VVRjgwd3gtTHJLbXluWHpRbzRUbEdTVE9icUc5b0xEamJpakQxT2hneklCZnRuX2ZwMXVaN1Z3Z1I0ejNZT0xvSDh1MzRSNW8?oc=5",
        "label": "NEUTRAL"
      },
      {
        "title": "Why Investors Shouldn't Be Surprised By Nintendo Co., Ltd.'s (TSE:7974) 34% Share Price Surge - simplywall.st",
        "url": "https://news.google.com/rss/articles/CBMixwFBVV95cUxQU0YteVRHV3BCM2xaNDFlam5sendUZmk2WEtlRUpBblVQOFhkajN1ME5NMnNxMnVPa0ZKbVJwQ1pOWGZDSEhyV3RmRkxSMDA2cE1XS2VGTmpQSU1GZHFuTE42emZLckZlMnBKOFR4eEJHZkJyS1RYWUhJOERQU2Q4enRuYjBnY0ZRYmpxMXQ5RHlJZTU2N1l6UGZsQmc3U29WZFlHdkFjakxDRWFmTDBKNUd5MmtOSTVHQlo3d1o0Sy1iNm9zU3ZJ0gHMAUFVX3lxTE9XWl9FNy1mYzhpU1l4X012MWdzb2FVS3lOaWNFN1pJY1VhcDJXeFNTR3JpY2tXSzROTURqNF9GUGhaR2N3WXZiVlRCelpnWE55ek1GZGJzTGN4aXN6YjY5QlhPN182bEprWlFJa2ZGUzhpVHAtUHRMdVpNRVVCNDJaWGtkMU5xZEtUQk56cXhERFJOTlVOVHZvSUx0cVBqYlhMSjF6MENSOGxQckxlUXE5LS1MMXpWRUo0NnBFWDRhYWd1OGZZeEVNX3NtSA?oc=5",
        "label": "NEUTRAL"
      },
      {
        "title": "Alphabet earnings, Fed comments, Nintendo Switch 2: What to Watch - Yahoo Finance",
        "url": "https://news.google.com/rss/articles/CBMijwFBVV95cUxPcHhBM3NsbkhacHRqRVhPWkxweTZwNkM0QXIwdlc5bk1uQkxaY3ZmMnJoY1BQQUUxY3h1SVBHLUJSYll5bjgtbERUQVBhaEpfSjI2NXMwY05QZ3BqaXFubzhQb2g3QkhoSExDVTNVYjVOSUJUT0Y1R05ocHYzc0ExLTBtYlM3ajlNRWV4aHVtQQ?oc=5",
        "label": "NEUTRAL"
      },
      {
        "title": "With 61% ownership in Nintendo Co., Ltd. (TSE:7974), institutional investors have a lot riding on the business - simplywall.st",
        "url": "https://news.google.com/rss/articles/CBMixwFBVV95cUxQaDZtYldCUENOSmxpY3ZIY01wblByMkpwbkxRaTdsNkZ4dWdTa2lDbklubE0zSzRmN3IxZkt0SVlEVGdkYkNxZ2oxZU1jb0duYzJIQ1cwLTlwMTNHZ0dtM3ljakpoa2NsQUZGdDJ2ZjVMclNCSEJOUG1fODZoZXhaSXF2N2dxQVF1OTZIamd2NHN1UlIyUFJwbHVUY3dxdmhtalFUMndZeldXeVh2Q2VMZ0lWY0hQTXA3M0RMRVZ4bnZYTG5vRk800gHMAUFVX3lxTFA1UkQxT3Mta2dBU0loN0h0QVBuQjRhRFNKc2RieUpjZ1NvS2lDS3hpNHdqNFZ5bkpTaExEVVd5MkFzUDRsMzJlZkpuM1JZRHduVFNDVFJndG9EMERUeDBKVmJ6VGxUbWppV2dsV29xZU9NYm5lZlZPMVlMc2lkWVh1bk9OZktfMUM0My1HVS1sM0M5UGR3WjRodkxCMWZPUmV0cVlEUzRxR2hXMXo2QVo5VWtwblBuZzRPaUVZdnJDSG1sMHhsazJUR2lBcg?oc=5",
        "label": "NEUTRAL"
      },
      {
        "title": "Nvidia's Jensen Huang says Nintendo Switch 2 has dedicated AI processors - CNBC",
        "url": "https://news.google.com/rss/articles/CBMickFVX3lxTE45UGp5Z2xIZDRmQUladWhJcWZWaVptSHlSSEFOcEF5Z2dpeFFQejJIRllGYmxEUzNsNUVrMmZzMndxMmMtbXB5bVh6UkptZ0JkcklrQnVQZktVWlRhc0huRGpwUHcwRkt1UnJNZWJDT0Npd9IBd0FVX3lxTE9aRGVqbUw4ZWJ0RXlpdzBFSlpuUEhqMWZOSXhxSE9WZUhRNUVtSFJMTWpjYWQwVHhualhQSGU2X2VQbXhKamxfSDU0YzU3Vzdsc2NsWTFKYTJLLXNXaGZsVVAtcXBXV2E1LU5VSFBxX3p3Y0lpcmRN?oc=5",
        "label": "NEUTRAL"
      },
      {
        "title": "Nintendo (TSE:7974) Is Due To Pay A Dividend Of ¥81.00 - simplywall.st",
        "url": "https://news.google.com/rss/articles/CBMiuwFBVV95cUxPRWk0czh0ZF9QMDR4aXhxSDRpaEptY09oQ0lkVXRjbVdpUVFpWTFTWVNrTVVlNkVJaWVBb1hfZXJrUWx3WmlFaF9TRkR1Y1ppcVpXVjVKZXd1NGZzZ3plOVZuVWRXR3V0WWVwNU5tLVBTZEdCczNPWWE0enlmRHBzU0NjYnZTemZqamJRRWxPSUpSMHdFaGFPMWJiT0xpYkRRY0FRV0VBSHd1b3VHWElrWWkwdzY1SndsbV9z0gHAAUFVX3lxTE1CemdJT3gzUnZvQmxfVnBrVXhBQ3g5QWdJRHVxUklEaFVCREkyNG5GWmUyXzhwakJHMVJQdVd6c0FZUUdwd0NPQ1E3aVdMTkxpMmxDRlJHTU9DMEhvcWFrVENlaTU1OHRLRDFzTE5ySWljTWg5UjQ1T2NtYmhpdUt4bHNyekJNLVVWMUJHR3dGUmJEOUJwV0JIcFh1UjI3Y1ZEV1oxaWVvcVdFMHFRdlZSRzRVTm5IaFc4ZGs4dHhtQg?oc=5",
        "label": "NEUTRAL"
      },
      {
        "title": "Nintendo delays Switch 2 preorders because of Trump tariffs - CNBC",
        "url": "https://news.google.com/rss/articles/CBMinwFBVV95cUxPZTVhOVN5VG81YmFJU3doenFTVUxYRF9vbGNPR2hxU29qcVphemZoRnJXT3RLT0ZhcjUyMEJrazlpVjRHS0JEcEFHb2xRUVVsRlVYOVN2dzdDUTAyTHhwNUZNY01lMFBLUHd5X0hORDJpaGZWQnc5b1R0UGNMdjkzcHRSNDRDWDRDZWtpMmtkeVY5WVpZRmx3TzQ2UnlHUEXSAaQBQVVfeXFMTUJuOHA1TWNUMGZqcUJjc0FSMURhcXNJLUJmZ1d1N1FWYkFiYkZrcjNuY1ZrTnV5dms3QlMtLW9FSjhGYnJKRFIxMDhOZkE1ODg4T3c1V1dmNGFkN2tXdV9PUWk0QW4taEg5N3hOdGplckhJMmZpWG1DYWlua0RzLW9FbGR1VEpfZUxHWTR0R2Y2TXYzSXZTZk5SLUJkajZNV2RrTjY?oc=5",
        "label": "NEGATIVE"
      },
      {
        "title": "Nintendo cuts Switch sales forecast ahead of successor device launch - Reuters",
        "url": "https://news.google.com/rss/articles/CBMiqgFBVV95cUxQZ3FGYzNDbGtzNkNTS2E5Z21NcThDbjZFZFQtRkRSWS1kcVRJX1BwS0VtcFVmUnNybHJYLVJnOF8wcXVjYWZNdkxHUjBkTEhveXJpak1yMTVvaEhkbGxvbkUtVkFjQU8zVlZXS2VYYWVwenJtNm5ObEVjakpNM0VpLUZSWnNibVhLaHVrNE9DRG5INy1pZkZXS1cybk9URGpyZXRUNjUtOEhEdw?oc=5",
        "label": "NEGATIVE"
      },
      {
        "title": "Nintendo kicks off Switch 2 preorders, Mario Kart World - Yahoo Finance",
        "url": "https://news.google.com/rss/articles/CBMif0FVX3lxTE5sVXVaMFRNbGhyU2IzZnpkcGhPYUkzaklVQjJMUVZrQTlxdS1nUEhMYnZXaXV0dmZYcm5GMGdqalhtYWhJME5iQk95RUhxZ0tLYlJOSUhpQnVhSlJZVFdqWmdXWGlCNnBzcjR4Um5ZSXB3RnRLc0VpVUt3RnN2NWs?oc=5",
        "label": "NEUTRAL"
      },
      {
        "title": "Nintendo forecasts sales of 15 million Switch 2 consoles as it gears up for launch - CNBC",
        "url": "https://news.google.com/rss/articles/CBMipAFBVV95cUxOaGtoYTRKaERSN0ZxaWdIMU15ZGRKa2ZpT3NUU3ZNeVVIdHJNR0NqZXpzd1oyaEJNa1Q1NnpSQzBHLWwyVkZIbHROZ2ZoUGpyV2QwNl9TUkhDY1g2b0Zia3NwRXMtemh2bmR4N09QSVlSeUtNaTNubUphTHFxeWF5MFdBLXFxQmZJc0RFU1RpR0RpUnZmUUNPV1pldUQ5Mkh0OU81ddIBqgFBVV95cUxQR2o0REVNamVPb2tuOGxoaEx5YXVVOEJaYTZGZkxTQUN4RFg5QUNQRF9yb1FwanhWSjNzM2dQWURzbDJOQUlzNy0td0F5Ym1sZVdzeTJHVlBfYnVHancybHZNakhwMzYtMEcyOEEydG1ETF9wUjVPUmJQWm9iRm8xYXByRUZXRVhtQVR0cEZnLW1mOVpGOE1vSUcxdVBYRU9PNTd0VUxJSmk0dw?oc=5",
        "label": "NEUTRAL"
      },
      {
        "title": "Nintendo profit plunges 69% as it cuts forecast for sales of ageing Switch console - CNBC",
        "url": "https://news.google.com/rss/articles/CBMirAFBVV95cUxNTzRzMmRSOGx0ZFROSTdvV0RBMHlCcTBDTkRkZ0ZuNW5QaGRtcVhPN3FVRFNGdXRuSGdFNFRaeEFLMmpDcWhpajR3cmlsbkR5enU2OTZvbHdGTXBMczR1WlhfdUg5OG9IbUtrbGNhaHJMRTQ1ZkhwNGRsN2M5VmF3NkpvQjhHOE9HRjhtcV8tVFI1c3NEaDdmQmRUcWItcmdPbXNwREFQRzVSX01q0gGyAUFVX3lxTE1sTjRTdXVKb0lrVmlQS1pBODIwLXhQd29oMm12YlBIYXU2cTVCc3NOVVZxUld0akxsM2FXOVUzZG1XTDZzcm03YlFjanhZMloxTTZ1NXZtaWxYQjZBbUxIdkV1VHY4SjlVWlpfNmNrQmI4RlpQaHdjWnNqMmNWYnAzOVl0N1Z5M2hleVZZRGxNanpLcTdYNVl6VHlFRnZteGpBVzdZTEs3ck8tdmZ2dE5KR1E?oc=5",
        "label": "NEGATIVE"
      },
      {
        "title": "Nintendo jumps 6% as it says current Switch games will be playable on the console's successor - CNBC",
        "url": "https://news.google.com/rss/articles/CBMipgFBVV95cUxPNGctRmVSZHVHM2lxcWpZTzBOSmtYdl9XbWE3Y2JPUEp5bTMwOWZKVlJEUmEyN2RMS1BWZWRLcVZLQ242R205czhzbUxvN3U4SWRJbnMtUXV6UlpCX1I0TkthN0FxNk91c2p2dFNzS052eEZ4WEJxbVl2QS13WVhGZThDNGpseUowQmJyTElTNEF4YWlSa3BkcnJJNjNtTW1HSzdtUlJ30gGrAUFVX3lxTFBWSnIzZS00Zlh5Wmg4cnhKN3hWeTZGWm9GbmE3TjM2dWR3MU1HU0NLWWQtUTdQTFJJNS1pSDBPUC1oZ2FjRS1pdjRfZThjb1FfUV9STXZRQ25wa3VZTGNqQWx0YU0xSHI4bEdnanRTMTE0WmdIWUFQWVE0ZjhXVTN4U1Btemdjam5MeWdocVNWNFRNbFlOR1pzeTRfMFFDbTFsdlJvTS1yUzR0QQ?oc=5",
        "label": "POSITIVE"
      },
      {
        "title": "Nintendo profit falls 55% as sales of its ageing Switch console plunge - CNBC",
        "url": "https://news.google.com/rss/articles/CBMiswFBVV95cUxQVTRVU0pQVFdXenZkdEJZZEkzTWwwcWs2MFE4QWY2ZlBzQUFvQWFfN0Rmai0yYmFYNk9CWVhPUnJ1MHNKMV9FQnhHejFDZ09ubm1la2swbVVDcmFrU2xyVXJfaTR1aTRrV3dudXd3LWNWNHo1T29YS3BLOU1TWnVjTHlmNnRPVTBzT01TaTF3Nnd0dE1RTXZ3bEpYZFBhTzl0Z2tsNERYVEQ5QkdvcGJlU2FxSdIBuAFBVV95cUxQRklWUnNWTWNQdDA1WjdKRHlPaGx5NkJTcGZHRVZvOWdxbEwtWGlSRWNrUHhQUlhnVjNrTUxoY1MtaHNHMDd2dWtlM0E3enJ4MzdFbHNZaDZLLXRFUXNwYkFqZzRQNUtKdWc4S0VfdnF4cEM5aUd3blFDNXRlYTcyeE1rb2FyRS0xR1dZcUxYN2VkWkxrb0ZNY1lSdVdkTTNpdWl4c3BfaU80anY5cDViZEd0dUhnRnlp?oc=5",
        "label": "NEGATIVE"
      },
      {
        "title": "Nintendo carries out 10-for-1 stock split to lure new investors to the Japanese gaming giant - CNBC",
        "url": "https://news.google.com/rss/articles/CBMiogFBVV95cUxPSkk4SFlzNFVmcHpXbkVTREdqeGxXN21FQ3RaZUQ1TDJFdXhCNWUzRVhhcFBLN2N6QUFTdmdDNThKNmFFN0dzeFRuUFRNUHBOenhYbERtbjNzVXVmTEJIQ09aZ3NScXRfbmh3RkpWQm5ISGx5bk54MDNMNXJHVUg2SjhySlVpVGcyNkZLdVN2UmVIdC1tQ242U0hpUFplMzVUaFHSAacBQVVfeXFMTUZnWjFJUXBqaE5ibC1tdlplbGhZSk9acXBvLXh6bmtxMDA1djFtU183NFctVHZudnlCQmZXRy1yaG5xLXdoeVBmZVpIVGhXUjBOYlZCUWNiWGMyODZzX2wzcGFtOGdPY0o3Unp5SzZMTGdsSloteHNRekw2MkJiS3dUTEt3blBzZWZXWXlISzJydnJuN0w5a1p6NFV2cjRvbEZVQ1VuQ2s?oc=5",
        "label": "POSITIVE"
      },
      {
        "title": "Nintendo announces surprise 10-for-1 stock split; expects Switch sales to fall 9% - CNBC",
        "url": "https://news.google.com/rss/articles/CBMirAFBVV95cUxNTllGWGhONW1IZmJhVGhNa1h6TWR2N1BfNjJYb0dselV3MG13SmZiYmRJbTZhd0JvODFzTnhwaENVQzBsbjdkNFRydWlWT09sMG1MRjR3NUJ5dVBtanRlWmU1WUFYN3NFVVNpT25mT1gtMzJfZjUxYktaaTdCaTgxOEVPenU4T29fZlptbFFnTld6M2x6OTdBSlZpMUxzWHV0YlRzRlB0MUgyUl9J0gGyAUFVX3lxTE5kUl9DeHZnY2ZUSTZPUnJYU0ZHUy1MakZ3WVVJS2EwcUlZeERuMHpjWFlkeHVkWEc5MTNhMXVLNUJMenJWTUF0aWVsWVlzQUlncEN4alZWOVJUcTFCRVZCeHo0WlBBbmFyRDBiMERqLTdsU2NDbHc3eVlRUWVxVFVBUVZHR2g1S2pyNlkwX1Z3Tmx0SHQyVUljWUJxd29CTXRIYmZFTXBCNEZKbldkY3dJRGc?oc=5",
        "label": "NEGATIVE"
      },
      {
        "title": "Nintendo shares fall nearly 6% after report that the Switch 2 will be delayed until 2025 - CNBC",
        "url": "https://news.google.com/rss/articles/CBMinAFBVV95cUxQbEhpOHdsV19CTjNibU9UQTZVcjAwZks0SFJiWkNUSTBTZHFLczB4UEQ5NEhNMGtoN2o1RW5DSWZNbzZnSFdBdGxINWtyVjRyc1NXOUw1RHFpUjRQc3ptZTcySF9jeDd1OTZadVpVdHBRQ0tqRXBOX1UzU000VWN5ZlppSExXWVNIcHlfM2J0WXBwX0phLWRBUGc1SUbSAaIBQVVfeXFMUEpBSnVBbmFxZmNxT0J4bGlja2VJb2l4UEhKZURBMXhwRlBuMEpBUjJ4ZXFVSnJhcmxjN3ZpZGZxZFBfOFNHN2dSLUwzUGd3WVN1VDA1b3c5NFNtc195dnVjMFlWOXNuV0xYYUpEdy1DNTcyajZWZ2hTb25GVE44SFVNRXlnNFRzc20xQk9BSHFjQjVCTHBkQTJTT0lKOGpJbTdn?oc=5",
        "label": "NEGATIVE"
      }
    ]
  },
  "extraction_date": "2025-06-13"
}