{
  "ticker": "8306.T",
  "name": "Mitsubishi UFJ Financial Group",
  "sector": "Financials",
  "market_cap": 22532688183296.0,
  "source_list": "Nikkei225",
  "fundamentals": {
    "PE": 12.302583,
    "PB": 1.1007245,
    "EV_Revenue": -2.698,
    "ROE": 0.09658,
    "ProfitMargin": 0.23273,
    "GrossMargin": 0.0,
    "DividendYield": 3.58,
    "DebtEquity": null,
    "CurrentRatio": null,
    "QuickRatio": null,
    "FreeCashFlow": null,
    "OperatingCashFlow": -4393666084864,
    "FCF_Margin": null,
    "ROA": 0.00479,
    "PEG": null,
    "EV_EBITDA": null,
    "BuybackYield": null,
    "PriceToFCF": null
  },
  "technical_indicators": {
    "RSI_14": 56.452334329457734,
    "Momentum_10": 1.0553410553410552,
    "MACD": 39.90985085661532,
    "BB_Percent": 0.5337403450021637,
    "SMA20_above_SMA50": 1.0
  },
  "scores": {
    "ValueScore": 0.9348013932398112,
    "QualityScore": 0.3933999108814709,
    "SignalScore": 0.5381333928260152
  },
  "volatility": 0.025600361135593,
  "beta": 0.244,
  "return_6m": 0.1046050051617486,
  "analyst_rating": {
    "recommendation": "buy",
    "analyst_count": 12,
    "target_mean_price": 2165.4167
  },
  "visual_data": {
    "sparkline": [
      {
        "date": "2024-12-06",
        "price": 1809.5
      },
      {
        "date": "2024-12-09",
        "price": 1814.0
      },
      {
        "date": "2024-12-10",
        "price": 1806.0
      },
      {
        "date": "2024-12-11",
        "price": 1842.0
      },
      {
        "date": "2024-12-12",
        "price": 1851.5
      },
      {
        "date": "2024-12-13",
        "price": 1849.5
      },
      {
        "date": "2024-12-16",
        "price": 1857.0
      },
      {
        "date": "2024-12-17",
        "price": 1821.0
      },
      {
        "date": "2024-12-18",
        "price": 1812.5
      },
      {
        "date": "2024-12-19",
        "price": 1834.5
      },
      {
        "date": "2024-12-20",
        "price": 1773.0
      },
      {
        "date": "2024-12-23",
        "price": 1800.0
      },
      {
        "date": "2024-12-24",
        "price": 1808.0
      },
      {
        "date": "2024-12-25",
        "price": 1800.0
      },
      {
        "date": "2024-12-26",
        "price": 1811.0
      },
      {
        "date": "2024-12-27",
        "price": 1832.5
      },
      {
        "date": "2024-12-30",
        "price": 1846.0
      },
      {
        "date": "2025-01-06",
        "price": 1857.5
      },
      {
        "date": "2025-01-07",
        "price": 1918.5
      },
      {
        "date": "2025-01-08",
        "price": 1919.0
      },
      {
        "date": "2025-01-09",
        "price": 1917.5
      },
      {
        "date": "2025-01-10",
        "price": 1903.5
      },
      {
        "date": "2025-01-14",
        "price": 1859.5
      },
      {
        "date": "2025-01-15",
        "price": 1892.5
      },
      {
        "date": "2025-01-16",
        "price": 1890.0
      },
      {
        "date": "2025-01-17",
        "price": 1867.5
      },
      {
        "date": "2025-01-20",
        "price": 1915.5
      },
      {
        "date": "2025-01-21",
        "price": 1918.0
      },
      {
        "date": "2025-01-22",
        "price": 1906.5
      },
      {
        "date": "2025-01-23",
        "price": 1907.0
      },
      {
        "date": "2025-01-24",
        "price": 1907.0
      },
      {
        "date": "2025-01-27",
        "price": 1921.0
      },
      {
        "date": "2025-01-28",
        "price": 1969.5
      },
      {
        "date": "2025-01-29",
        "price": 1969.5
      },
      {
        "date": "2025-01-30",
        "price": 1964.5
      },
      {
        "date": "2025-01-31",
        "price": 1978.5
      },
      {
        "date": "2025-02-03",
        "price": 1926.0
      },
      {
        "date": "2025-02-04",
        "price": 1941.5
      },
      {
        "date": "2025-02-05",
        "price": 1930.0
      },
      {
        "date": "2025-02-06",
        "price": 1912.5
      },
      {
        "date": "2025-02-07",
        "price": 1911.0
      },
      {
        "date": "2025-02-10",
        "price": 1900.5
      },
      {
        "date": "2025-02-12",
        "price": 1906.5
      },
      {
        "date": "2025-02-13",
        "price": 1942.0
      },
      {
        "date": "2025-02-14",
        "price": 1943.5
      },
      {
        "date": "2025-02-17",
        "price": 1982.5
      },
      {
        "date": "2025-02-18",
        "price": 2022.0
      },
      {
        "date": "2025-02-19",
        "price": 2011.5
      },
      {
        "date": "2025-02-20",
        "price": 1972.5
      },
      {
        "date": "2025-02-21",
        "price": 1949.5
      },
      {
        "date": "2025-02-25",
        "price": 1960.5
      },
      {
        "date": "2025-02-26",
        "price": 1920.0
      },
      {
        "date": "2025-02-27",
        "price": 1940.5
      },
      {
        "date": "2025-02-28",
        "price": 1903.0
      },
      {
        "date": "2025-03-03",
        "price": 1948.5
      },
      {
        "date": "2025-03-04",
        "price": 1932.0
      },
      {
        "date": "2025-03-05",
        "price": 1927.5
      },
      {
        "date": "2025-03-06",
        "price": 1954.5
      },
      {
        "date": "2025-03-07",
        "price": 1922.5
      },
      {
        "date": "2025-03-10",
        "price": 1920.0
      },
      {
        "date": "2025-03-11",
        "price": 1893.0
      },
      {
        "date": "2025-03-12",
        "price": 1930.0
      },
      {
        "date": "2025-03-13",
        "price": 1957.0
      },
      {
        "date": "2025-03-14",
        "price": 2000.5
      },
      {
        "date": "2025-03-17",
        "price": 2030.0
      },
      {
        "date": "2025-03-18",
        "price": 2106.0
      },
      {
        "date": "2025-03-19",
        "price": 2105.5
      },
      {
        "date": "2025-03-21",
        "price": 2226.0
      },
      {
        "date": "2025-03-24",
        "price": 2181.5
      },
      {
        "date": "2025-03-25",
        "price": 2163.5
      },
      {
        "date": "2025-03-26",
        "price": 2159.0
      },
      {
        "date": "2025-03-27",
        "price": 2178.5
      },
      {
        "date": "2025-03-28",
        "price": 2108.5
      },
      {
        "date": "2025-03-31",
        "price": 2011.0
      },
      {
        "date": "2025-04-01",
        "price": 1994.0
      },
      {
        "date": "2025-04-02",
        "price": 1963.5
      },
      {
        "date": "2025-04-03",
        "price": 1823.0
      },
      {
        "date": "2025-04-04",
        "price": 1668.5
      },
      {
        "date": "2025-04-07",
        "price": 1495.5
      },
      {
        "date": "2025-04-08",
        "price": 1658.0
      },
      {
        "date": "2025-04-09",
        "price": 1570.0
      },
      {
        "date": "2025-04-10",
        "price": 1711.0
      },
      {
        "date": "2025-04-11",
        "price": 1644.5
      },
      {
        "date": "2025-04-14",
        "price": 1647.0
      },
      {
        "date": "2025-04-15",
        "price": 1684.0
      },
      {
        "date": "2025-04-16",
        "price": 1642.0
      },
      {
        "date": "2025-04-17",
        "price": 1680.0
      },
      {
        "date": "2025-04-18",
        "price": 1685.5
      },
      {
        "date": "2025-04-21",
        "price": 1653.0
      },
      {
        "date": "2025-04-22",
        "price": 1633.0
      },
      {
        "date": "2025-04-23",
        "price": 1687.5
      },
      {
        "date": "2025-04-24",
        "price": 1721.5
      },
      {
        "date": "2025-04-25",
        "price": 1735.0
      },
      {
        "date": "2025-04-28",
        "price": 1772.0
      },
      {
        "date": "2025-04-30",
        "price": 1803.5
      },
      {
        "date": "2025-05-01",
        "price": 1782.0
      },
      {
        "date": "2025-05-02",
        "price": 1737.5
      },
      {
        "date": "2025-05-07",
        "price": 1750.5
      },
      {
        "date": "2025-05-08",
        "price": 1763.5
      },
      {
        "date": "2025-05-09",
        "price": 1811.0
      },
      {
        "date": "2025-05-12",
        "price": 1839.5
      },
      {
        "date": "2025-05-13",
        "price": 1907.5
      },
      {
        "date": "2025-05-14",
        "price": 1945.0
      },
      {
        "date": "2025-05-15",
        "price": 1930.0
      },
      {
        "date": "2025-05-16",
        "price": 1947.0
      },
      {
        "date": "2025-05-19",
        "price": 1969.5
      },
      {
        "date": "2025-05-20",
        "price": 1974.5
      },
      {
        "date": "2025-05-21",
        "price": 1970.0
      },
      {
        "date": "2025-05-22",
        "price": 1945.0
      },
      {
        "date": "2025-05-23",
        "price": 1942.5
      },
      {
        "date": "2025-05-26",
        "price": 1955.0
      },
      {
        "date": "2025-05-27",
        "price": 1977.0
      },
      {
        "date": "2025-05-28",
        "price": 1963.0
      },
      {
        "date": "2025-05-29",
        "price": 2005.0
      },
      {
        "date": "2025-05-30",
        "price": 2025.5
      },
      {
        "date": "2025-06-02",
        "price": 1990.0
      },
      {
        "date": "2025-06-03",
        "price": 1977.0
      },
      {
        "date": "2025-06-04",
        "price": 1980.5
      },
      {
        "date": "2025-06-05",
        "price": 1953.0
      },
      {
        "date": "2025-06-06",
        "price": 1963.0
      }
    ],
    "current_price_data": {
      "price": 1963.0,
      "change": 10.0,
      "percent_change": 0.51
    }
  },
  "news_sentiment": {
    "summary": "L'actualité récente met en lumière des tendances contrastées pour les entreprises japonaises. Alors que les obligations japonaises ont progressé et que Mitsubishi UFJ Financial Group suscite un intérêt croissant, les actions des banques japonaises sont malmenées en raison des craintes liées aux tarifs américains et aux signes de récession mondiale. D'un côté, des mouvements stratégiques importants sont observés, tels que l'acquisition de WealthNavi par MUFG, le lancement de l'offre publique de rachat de ses propres actions par Toyota et l'expansion européenne de MUFG. En revanche, des cessions d'actifs significatives, comme la vente des parts stratégiques de Toyota détenues par les banques japonaises, interviennent. Ces événements reflètent une volatilité accrue sur les marchés financiers japonais, influencée par des facteurs locaux et mondiaux.",
    "sentiment_score": 0.056,
    "label": "NEGATIVE",
    "positive_ratio": 0.22,
    "neutral_ratio": 0.61,
    "negative_ratio": 0.17,
    "bullet_positive_count": 0,
    "bullet_negative_count": 0,
    "headlines": [
      {
        "title": "Japanese Bonds Rise as 30-Year Auction Brings Some Relief - Yahoo",
        "url": "https://news.google.com/rss/articles/CBMihgFBVV95cUxQOG14dm9uYWhYZnAtS2hubUtCQXA1anFoVWZGUEZOTXM2OFlrUGVDQklfWUI1T2RTTFhzbG9jc0FZS0dKeUp3NUZ6S294ZmJTSVhZZWtDZlVJcHkyWHVQY3pocE1CTXIyeGxtTzhiZjV4dS1ycWd4bXluaUVIMC1ZMEV3LTVCdw?oc=5",
        "label": "POSITIVE"
      },
      {
        "title": "Here's Why We Think Mitsubishi UFJ Financial Group (TSE:8306) Is Well Worth Watching - simplywall.st",
        "url": "https://news.google.com/rss/articles/CBMi5AFBVV95cUxQb0tyNUEwVjliSnNFYkpDRWVTTUJMakczQXluUm5NOEY1ZkRkMEtuMHFqYVF5dVVGR1l6TnFpdnNxNC1SdjRralpzVmhBOVNjYkN4elozN3dkaVNhbjFFUnlzaGhyVzZBY1FnbHg0Vlpnc21lWG95RnExeHFEWHk2Sm5FeGdDTUFrek4wbXF5ckxxMGU3MDJHUWE1MlBuRU5BMHhuZEZMMEJpMUFPWHlkbHA1d2ZRWlZFVzRKLXc2YnZsbjdIcEJIelRVcldncjkxRTNXV1dXbF93Y2htMXdnLXBEbXDSAeoBQVVfeXFMUHN4VG5EV253aGd0MFEzbGVJTzkteGlBc1I5LVVFM1JqZlU3MlI5Q2tqWkZ4YTRTSHVCYS1PYTU0c2ZyVThfZXBQTUJYUWdGRkd2RWdjYzMySDBFbk5DSk8wT3V4aTVVWU5teGVnSGNjVTFXVVgyU25jT242OTlEOGJGVGgzZmEyS3BMWmJiazhRN0hYeXBzRGllMWlBbElPQnhQbXVKQ29lcTVqSkZNMnFmNmhNa3c1MkcyMno1RGE0SWhKVWNQMXBYNVpLNndlWndQMmxNTFlUamdSbVZuTEp1MW9XcnZVZ2ZB?oc=5",
        "label": "NEUTRAL"
      },
      {
        "title": "Japanese bank shares hammered as US tariffs spur fears about country's fragile recovery - Reuters",
        "url": "https://news.google.com/rss/articles/CBMitwFBVV95cUxQeXFyZ3gtN2pScEVPeU84aS1jZTlxdFdKMXZFUHFtZ2xodmVjSmlJMG9ZamFiMGVjbnVIVmJRM2ZuSEozczJBNXNGLTRrdUVLbUlUa29NZnNaQzVReUtfSXRwSkdxWEVNQ21KRW53SWtkVHVJbW5LdUpvRWtHR2N0TDdaNDVDaWdUdE1EZ09kYTNxMkJmU2RZTlNHeTNuTEt6RHQ3ZlFmdnBNN3F0Zy1odTdZMVg3RXM?oc=5",
        "label": "NEGATIVE"
      },
      {
        "title": "Global rout in bank shares intensifies as recession fears mount - KITCO",
        "url": "https://news.google.com/rss/articles/CBMirAFBVV95cUxNQW1HVnFKZnJrZmhyS1pfNHdoN1E1TUstN3BEVmdHdjVHQ2JGT2RMbThjaEtWeGFMbDFyaWhNcXZYWnNndEh6Y1IyR1BXNzBsTHdQT2hWdmlvb0VDRHE4djRHZXpwVGF1YXRhNXBVTTBYNUh5SHBLT2gxWi1JVDVkc1Q0NzdHVGY3ZThJb3JkS2tGUmp1UGdjVFJwR09zbE5QVW1oU0VucC1XRHE1?oc=5",
        "label": "NEGATIVE"
      },
      {
        "title": "Japan’s Nikkei Stock Average Ends at 2-week Low as Automakers Slump on US Tariff Worries (Update1) - The Japan News",
        "url": "https://news.google.com/rss/articles/CBMiekFVX3lxTE5UbWV2X1pVMmtUSWRSQkFLb1F4WTBCMXJDTUs1R3dMZjJrVGtOOGdyazREblJmS3JOaHM1eXdMOGd0QkFmVDhyWERYTndzQVg4dGNGcHRRZDdEemFsYmdST0FlUVBHc0R6X3dVY2pKTWdNLW1oVXB3S2Vn?oc=5",
        "label": "NEGATIVE"
      },
      {
        "title": "Japan's MUFG to spend over $660 million to buy robo-adviser WealthNavi - Reuters",
        "url": "https://news.google.com/rss/articles/CBMisgFBVV95cUxPUmdQcTZ4UmVDdTlmVktrQ2ZydVo4U1l1eUt0YWVsOUotRHg2TDB6bUtBM3VtZVdwLWczYUFhUEZPOVA1SFNpX09lOV92QWRiOEZWRTV3dkZkeHROdGItY1VOOXJpR2hfN2drUjFBRXlxeGR4MzFNZHJZdHNGd2JnOFYzZTk2Y2RNRGpVM3Y1cmY0d1V5R0RjWE9vamNDVk1OQWQ1NzIwYzBYbUt1Vk9lVzZB?oc=5",
        "label": "NEUTRAL"
      },
      {
        "title": "8306 Stock Price and Chart — TSE:8306 - TradingView",
        "url": "https://news.google.com/rss/articles/CBMiWEFVX3lxTE81QTZGNTRuWXRPWkt0MjBoaVI1U1J3MThPX0pVUmhPd0FvUzBKel9rMjhXOUVpd0E4WmQwVGpKNUNyam1IbkV2WGFQQ0dUeURfaEVKbUQ1eHg?oc=5",
        "label": "NEUTRAL"
      },
      {
        "title": "Japan's MUFG to promote bank unit chief Mike to president - source - Yahoo",
        "url": "https://news.google.com/rss/articles/CBMirAFBVV95cUxQWlZhU3FQSWVBYjhoTzVuVnl3ZFNhd2dfWndhOWpBYzRtMnAyeFZ4cndmT1ZSaFlGZEFrd0M5T1BuUW94MmVtOV9TeG9xbm1yckJ4Nk9EdHVwQmxXN0dacDJZNnFmbHE0ZExvZHU5Z3pBb1ozTnp1al85bXhGeThKU052SzRfMGo5ZG85TEpmcG0wNGhQRnhrUW9oVks1R2ZkMks1LWNVdC1TWHVK?oc=5",
        "label": "NEUTRAL"
      },
      {
        "title": "Toyota to launch $5.16 billion tender offer for own shares - Reuters",
        "url": "https://news.google.com/rss/articles/CBMisAFBVV95cUxOY2UtVE5Lb05qOExheDhFWk5HYlBZMlpoM2Roek1JU293c3RzTk8tNVo4ZUwzeUkxMU9US3BRamxCVm5GaUN0T1lCMUgtVW5MTHo3ODRkemxadFJJY3pRR1Rub1hzT2YwQmtSZ1lrTkR6UTc0M0JTc25nbVVucHhQX3RhWnVXOGQzdFdxU0dreFE0MlVBbFhmejV5QmhfYkNHWExaQThndmFjcHRVNHlSMw?oc=5",
        "label": "NEUTRAL"
      },
      {
        "title": "Japan's SMFG plans to buy 10% stake in SBI worth over $443 mln - Asia Business Outlook",
        "url": "https://news.google.com/rss/articles/CBMitgFBVV95cUxQMXNCR3NzZTNYa2VPZ3BmOERHTlduZU96NzZXWmxyN1l2VTBzSjFZUGszeWdEamMwY1ZSby1zTTJYeU10cGhFaGVyU19ZWFVNSVBYSWc3WmNnOXBnVVlOeUsxSnAyNlZHeF9ZVVdYUy1aNHhtTjNiVFVaSi0wdHpmMC1QWVVKSjN0YkRPNXhJOEd3VjYwWi1EM3p6WTdEdFIwQlFhdUFtQWpWZ1ZIU1R6d0U2UnZBZw?oc=5",
        "label": "NEUTRAL"
      },
      {
        "title": "SVB: U.S. Authorities Launch Emergency Measures to Enhance Banking System - Voice of Nigeria",
        "url": "https://news.google.com/rss/articles/CBMitwFBVV95cUxPS0NnTFFfOXViT0o5VGwweWExdFV3eTdWd3BYUmR2MEZfMWsxaW9kTFVlWElvaVo2Mmdrb21SVlRZRG1udFplUjFiRzFtRjdscHlVdUhOMTJ1YTdjYk0yMHZmRGRJczhLOVNfWmQ2ZHJ2cndxbVliVnJMclJ2a3l6WkNKYjVsTlpjT2JmcW1DQzY5dXF6LU81dWUyWUJUOVhCM3ViSVg5ek9QQmZQbVFndXpXbzloLWvSAbcBQVVfeXFMT0tDZ0xRXzl1Yk9KOVRsMHlhMXRVd3k3VndwWFJkdjBGXzFrMWlvZExVZVhJb2laNjJna29tUlZUWURtbnRaZVIxYkcxbUY3bHB5VXVITjEydWE3Y2JNMjB2ZkRkSXM4SzlTX1pkNmRydnJ3cW1ZYlZyTHJSdmt5elpDSmI1bE5aY09iZnFtQ0M2OXVxei1PNXVlMllCVDlYQjN1YklYOXpPUEJmUG1RZ3V6V285aC1r?oc=5",
        "label": "POSITIVE"
      },
      {
        "title": "Gotrade, the app that lets international users buy fractions of US stocks, raises $15.5M Series A - Yahoo Finance",
        "url": "https://news.google.com/rss/articles/CBMiigFBVV95cUxOdHBfT21ENTNoZkVrS0VlbjhmbGNSMzExNzJFYXh1ejdHSUM2emY2UU5KOEpoV1FVNnFIM2E3MWtsNGpJbGw5VklQWC1tZG9UaUJWcWRObEQ2bWtkWnJWOWpqNnJzdXd5U0ZsN3E4WGxnR3A1NXpQNURnQk5OY3NyZlNDb1lmMmxOY2c?oc=5",
        "label": "POSITIVE"
      },
      {
        "title": "Japan banks to begin divesting their strategic Toyota shareholdings, Bloomberg reports - Reuters",
        "url": "https://news.google.com/rss/articles/CBMiuwFBVV95cUxNWlNTa3Y5bDlVcnNMM0xndzFlRWJyZWVjOTJicUQwdHdSaWZzamdOcmhsY1ZnMmt0RXR0X0hfSms2dWx5aTV5cVJYVVpJems3TGEyWlFVQUJmck1BQjlRVkk3SW54aXBzTXFZb0lSelN3Wk92TjItRnFMclprdklHR2E2QkVNeVRaNkZ1VmdXd014MzIwb01mM3hEZVNVUUdPaU1jUDJKRU9VdVlBck9QaFBqOHdLUGJibnM4?oc=5",
        "label": "NEUTRAL"
      },
      {
        "title": "Japan's MUFG hires 180 staff in London in Europe expansion drive - Yahoo Life UK",
        "url": "https://news.google.com/rss/articles/CBMirgFBVV95cUxNZzJhWUtucHZuTjlzbEZDZDhGc2FyRndQdkN3cHNqQnhoTTdMZGhsUXg3VmtEQXVzeDRObjA5VllkNGg1T0pxU0p0T053U2lLekRET2VjN2thMEtqUWJkLWJZNXJfUC11TVNIUTFnYk41VTFkLWdGME1uQTBVeWNvVlVZelROWVBPWldISFZmRDhDWlh5MW5kWVpyX190UU9ZVVFnT3ZxSTRMWHVUS3c?oc=5",
        "label": "NEUTRAL"
      },
      {
        "title": "MUFG to buy BofA Merrrill Lynch's stake in Japan private banking joint venture - Reuters",
        "url": "https://news.google.com/rss/articles/CBMizgFBVV95cUxPdF85YWppd2hncVhCUmNCV3RFdnp2WTJKX1Y5MHZBQUFKTkFyeVpIS0ZkTFdmcVJqczVXTkNmUXRpU29IeDZVSHk5ajRLWGxxdEttR2hkeTNpak1uQ2tsMFhEWDg1Wm5lbDdtZ3l0T25JNF9BSTZ2VnZSWUMwaEI2cFQxZnluQUxQU3l3ZktFZlI3eXpJejlyRVBQM2tLV0piMWJTZU5rNUdQQWQ5RTUzeUZIVEZ6TmtFNlpQLWJaRGVzUnVHbUVTbVozZmZLUQ?oc=5",
        "label": "NEUTRAL"
      },
      {
        "title": "Japan's NTT launches $40 billion buyout of wireless unit Docomo - Reuters",
        "url": "https://news.google.com/rss/articles/CBMiuwFBVV95cUxNVG5hSzdFNktOWTBXelUwQnp6QUZXVENURTctMkk2b0F5R2dId3ZGUGgyT3g1eGtSZThCRWl1R0t6Tzd6Z1d2TnhjM09uRHZDUDltZFdfR2RnTmk4aW44eDlGcXAwekFsSjhpcXY2QV9ldzFYZXI3ZEVacG5iWVhxVDhiY2RFaUVFSlRnc1FXMkRGQ09UMFFTTGZTdGNLSTVvSncxOG54WUZ3SGZ0aFFCdVg2WDZscmQtMjcw?oc=5",
        "label": "NEUTRAL"
      },
      {
        "title": "Toyota Motor Corp and Mitsubishi UFJ lead high-volume stocks in Japan with over 3% gains - Business Upturn",
        "url": "https://news.google.com/rss/articles/CBMi3wFBVV95cUxPNlBiNFFJSTNkS2E0NlYwWmlwNnZKdTR1WDN6R3J2VXF5OUNINElCcEwwZDJhZ09sTkZfX1NmWXRoM0VuOHp6VHVmYVJtS3dQeGtGc3lmWkI0dE5uaXQtTExJcGlEWi11TVMwLThqQ1NBZkZtVDl0aFhJdXhmTXhrSWpmSXVDcWUyQ1BfOGpWdHpPMndjQUhzWWxoeVlmZnBsV3RoRGJ5ZXFDWF9tTXJBNEVQN2d4U2wxNkJDRmswLXRFbXdFMUttQ2ZsV01MbHh4V1lCNEo2bWFuY0hRcFFN?oc=5",
        "label": "POSITIVE"
      },
      {
        "title": "Lixil to buy Grohe in $4 billion landmark deal - Reuters",
        "url": "https://news.google.com/rss/articles/CBMiowFBVV95cUxOTmlPbWlaR1JlYWNZcklENmtUTGVFc0haN3hzR3BQeFlibm4xUFJVbThHQ1R4NGpTaXFjYm16ZlkzMjlxQmlkRG5leEd4Ym1sWDRTc0RBRWo1ckhNcjA5VFhqZ0RHSERkTkw2dGV2dnBkaVZjWUtaWHh5ejAxcUFFRHozSUNpZ2NPUHREZzk3aTU2b2xZeXVLS2tRQW83VHkzV21V?oc=5",
        "label": "NEUTRAL"
      }
    ]
  },
  "extraction_date": "2025-06-06"
}